flexitools/__init__.py
flexitools/flexitools.py
flexitools-0.1.3.dist-info/LICENSE
flexitools-0.1.3.dist-info/METADATA
flexitools-0.1.3.dist-info/WHEEL
flexitools-0.1.3.dist-info/top_level.txt
flexitools-0.1.3.dist-info/RECORD
