Metadata-Version: 2.1
Name: flexitools
Version: 0.1.3
Summary: Encrypts/decrypts messages and includes games of Rock, Paper, Scissors (RPS) and Snake, Water, Gun (SWG).
Author: Mohammad Sabbir Hosen
Author-email: hellowsabbir@gmail.com
License: MIT
License-File: LICENSE
